{
  "updated": "Jul 1, 4:33 AM ET",
  "matchupPeriod": 14,
  "currentPeriod": 99,
  "weekStartPeriod": 97,
  "totalPeriods": 7,
  "spCap": 13,
  "weekLabel": "14",
  "dateRange": "Jun 29\u2013Jul 5, 2026",
  "apTotal": 143,
  "matchups": [
    {
      "away": "IR",
      "home": "RM"
    },
    {
      "away": "JK",
      "home": "AA"
    },
    {
      "away": "SP",
      "home": "DH"
    },
    {
      "away": "SK",
      "home": "MM"
    },
    {
      "away": "MN",
      "home": "TB"
    },
    {
      "away": "WG",
      "home": "BB"
    }
  ],
  "history": [
    [
      "RM",
      "SP",
      "SP",
      1,
      505.0,
      595.5
    ],
    [
      "JK",
      "SK",
      "JK",
      1,
      812.5,
      643.0
    ],
    [
      "IR",
      "MN",
      "IR",
      1,
      755.0,
      723.0
    ],
    [
      "AA",
      "WG",
      "WG",
      1,
      646.5,
      656.5
    ],
    [
      "DH",
      "BB",
      "DH",
      1,
      603.5,
      522.5
    ],
    [
      "MM",
      "TB",
      "MM",
      1,
      567.5,
      506.0
    ],
    [
      "JK",
      "RM",
      "RM",
      2,
      334.0,
      484.0
    ],
    [
      "SP",
      "IR",
      "IR",
      2,
      484.5,
      538.5
    ],
    [
      "SK",
      "AA",
      "AA",
      2,
      390.0,
      537.0
    ],
    [
      "MN",
      "DH",
      "MN",
      2,
      546.5,
      300.5
    ],
    [
      "WG",
      "MM",
      "MM",
      2,
      354.5,
      467.5
    ],
    [
      "BB",
      "TB",
      "TB",
      2,
      325.5,
      363.0
    ],
    [
      "RM",
      "IR",
      "IR",
      3,
      321.5,
      554.0
    ],
    [
      "AA",
      "JK",
      "JK",
      3,
      296.0,
      475.5
    ],
    [
      "DH",
      "SP",
      "DH",
      3,
      510.5,
      468.0
    ],
    [
      "MM",
      "SK",
      "MM",
      3,
      475.0,
      377.5
    ],
    [
      "TB",
      "MN",
      "TB",
      3,
      481.5,
      401.0
    ],
    [
      "BB",
      "WG",
      "BB",
      3,
      478.0,
      394.0
    ],
    [
      "AA",
      "RM",
      "RM",
      4,
      391.5,
      429.5
    ],
    [
      "IR",
      "DH",
      "IR",
      4,
      411.0,
      310.0
    ],
    [
      "JK",
      "MM",
      "MM",
      4,
      392.0,
      461.5
    ],
    [
      "SP",
      "TB",
      "TB",
      4,
      458.0,
      501.5
    ],
    [
      "SK",
      "BB",
      "BB",
      4,
      369.0,
      469.0
    ],
    [
      "MN",
      "WG",
      "WG",
      4,
      501.0,
      508.0
    ],
    [
      "RM",
      "DH",
      "DH",
      5,
      407.0,
      438.5
    ],
    [
      "MM",
      "AA",
      "AA",
      5,
      449.0,
      494.5
    ],
    [
      "TB",
      "IR",
      "IR",
      5,
      327.5,
      409.5
    ],
    [
      "BB",
      "JK",
      "BB",
      5,
      476.5,
      276.5
    ],
    [
      "WG",
      "SP",
      "WG",
      5,
      469.5,
      434.0
    ],
    [
      "MN",
      "SK",
      "SK",
      5,
      409.0,
      414.5
    ],
    [
      "MM",
      "RM",
      "MM",
      6,
      401.0,
      352.0
    ],
    [
      "DH",
      "TB",
      "TB",
      6,
      376.0,
      379.5
    ],
    [
      "AA",
      "BB",
      "AA",
      6,
      413.5,
      333.0
    ],
    [
      "IR",
      "WG",
      "IR",
      6,
      443.5,
      381.0
    ],
    [
      "JK",
      "MN",
      "JK",
      6,
      458.5,
      428.0
    ],
    [
      "SP",
      "SK",
      "SK",
      6,
      392.0,
      468.5
    ],
    [
      "RM",
      "TB",
      "RM",
      7,
      416.0,
      367.0
    ],
    [
      "BB",
      "MM",
      "BB",
      7,
      406.0,
      370.5
    ],
    [
      "WG",
      "DH",
      "WG",
      7,
      427.5,
      399.0
    ],
    [
      "MN",
      "AA",
      "MN",
      7,
      444.0,
      403.0
    ],
    [
      "SK",
      "IR",
      "SK",
      7,
      433.5,
      397.5
    ],
    [
      "SP",
      "JK",
      "SP",
      7,
      539.0,
      488.0
    ],
    [
      "BB",
      "RM",
      "BB",
      8,
      460.5,
      373.5
    ],
    [
      "TB",
      "WG",
      "WG",
      8,
      350.5,
      467.5
    ],
    [
      "MM",
      "MN",
      "MM",
      8,
      425.5,
      397.0
    ],
    [
      "DH",
      "SK",
      "DH",
      8,
      474.0,
      446.5
    ],
    [
      "AA",
      "SP",
      "AA",
      8,
      402.0,
      284.0
    ],
    [
      "IR",
      "JK",
      "IR",
      8,
      472.0,
      361.5
    ],
    [
      "RM",
      "WG",
      "WG",
      9,
      278.0,
      514.5
    ],
    [
      "MN",
      "BB",
      "BB",
      9,
      452.0,
      497.0
    ],
    [
      "SK",
      "TB",
      "TB",
      9,
      458.5,
      501.5
    ],
    [
      "SP",
      "MM",
      "SP",
      9,
      534.5,
      399.5
    ],
    [
      "JK",
      "DH",
      "JK",
      9,
      468.0,
      337.5
    ],
    [
      "IR",
      "AA",
      "AA",
      9,
      385.0,
      409.0
    ],
    [
      "MN",
      "RM",
      "MN",
      10,
      426.5,
      348.5
    ],
    [
      "WG",
      "SK",
      "WG",
      10,
      472.5,
      394.5
    ],
    [
      "BB",
      "SP",
      "SP",
      10,
      389.5,
      455.0
    ],
    [
      "TB",
      "JK",
      "JK",
      10,
      281.0,
      386.5
    ],
    [
      "MM",
      "IR",
      "MM",
      10,
      496.5,
      411.0
    ],
    [
      "DH",
      "AA",
      "DH",
      10,
      387.0,
      341.0
    ],
    [
      "RM",
      "SK",
      "RM",
      11,
      406.5,
      397.5
    ],
    [
      "SP",
      "MN",
      "MN",
      11,
      331.0,
      504.0
    ],
    [
      "JK",
      "WG",
      "JK",
      11,
      468.5,
      402.0
    ],
    [
      "IR",
      "BB",
      "BB",
      11,
      477.0,
      508.5
    ],
    [
      "AA",
      "TB",
      "AA",
      11,
      433.0,
      360.0
    ],
    [
      "DH",
      "MM",
      "MM",
      11,
      436.0,
      456.5
    ],
    [
      "SP",
      "RM",
      "SP",
      12,
      433.0,
      387.0
    ],
    [
      "SK",
      "JK",
      "JK",
      12,
      378.5,
      399.0
    ],
    [
      "MN",
      "IR",
      "IR",
      12,
      456.0,
      464.5
    ],
    [
      "WG",
      "AA",
      "AA",
      12,
      408.5,
      481.5
    ],
    [
      "BB",
      "DH",
      "DH",
      12,
      447.0,
      502.0
    ],
    [
      "TB",
      "MM",
      "MM",
      12,
      219.0,
      506.0
    ],
    [
      "RM",
      "JK",
      "JK",
      13,
      483.0,
      538.0
    ],
    [
      "IR",
      "SP",
      "SP",
      13,
      369.0,
      400.5
    ],
    [
      "AA",
      "SK",
      "AA",
      13,
      433.5,
      373.5
    ],
    [
      "DH",
      "MN",
      "DH",
      13,
      436.5,
      287.5
    ],
    [
      "MM",
      "WG",
      "WG",
      13,
      403.0,
      485.0
    ],
    [
      "TB",
      "BB",
      "BB",
      13,
      469.5,
      559.0
    ]
  ],
  "catStats": {
    "WG": {
      "sb": 76.0,
      "hb": 28.0,
      "qs": 71.0,
      "r": 588.0,
      "kP": 1044.0,
      "rbi": 723.0,
      "gw": 36.0,
      "w": 65.0,
      "s": 596.0,
      "hr": 181.0,
      "hbp": 14.0,
      "er": 520.0,
      "cs": 72.0,
      "bs": 15.0,
      "hd": 66.0,
      "bbP": 370.0,
      "bbB": 224.0,
      "t": 35.0,
      "hP": 1052.0,
      "l": 53.0,
      "so": 0.0,
      "d": 175.0,
      "sac": 24.0,
      "sv": 45.0,
      "ip": 1124.0,
      "kB": 403.0
    },
    "BB": {
      "sb": 80.0,
      "hb": 50.0,
      "qs": 63.0,
      "r": 627.0,
      "kP": 1101.0,
      "rbi": 706.0,
      "gw": 53.0,
      "w": 80.0,
      "s": 659.0,
      "hr": 181.0,
      "hbp": 13.0,
      "er": 566.0,
      "cs": 79.0,
      "bs": 13.0,
      "hd": 61.0,
      "bbP": 461.0,
      "bbB": 211.0,
      "t": 51.0,
      "hP": 1111.0,
      "l": 48.0,
      "so": 0.0,
      "d": 180.0,
      "sac": 17.0,
      "sv": 14.0,
      "ip": 1167.3,
      "kB": 500.0
    },
    "RM": {
      "sb": 72.0,
      "hb": 13.0,
      "qs": 66.0,
      "r": 514.0,
      "kP": 1016.0,
      "rbi": 616.0,
      "gw": 38.0,
      "w": 59.0,
      "s": 535.0,
      "hr": 156.0,
      "hbp": 20.0,
      "er": 461.0,
      "cs": 72.0,
      "bs": 10.0,
      "hd": 49.0,
      "bbP": 352.0,
      "bbB": 186.0,
      "t": 49.0,
      "hP": 905.0,
      "l": 55.0,
      "so": 1.0,
      "d": 159.0,
      "sac": 21.0,
      "sv": 39.0,
      "ip": 997.0,
      "kB": 443.0
    },
    "TB": {
      "sb": 91.0,
      "hb": 9.0,
      "qs": 53.0,
      "r": 490.0,
      "kP": 934.0,
      "rbi": 696.0,
      "gw": 48.0,
      "w": 81.0,
      "s": 493.0,
      "hr": 126.0,
      "hbp": 10.0,
      "er": 497.0,
      "cs": 64.0,
      "bs": 12.0,
      "hd": 53.0,
      "bbP": 395.0,
      "bbB": 191.0,
      "t": 55.0,
      "hP": 983.0,
      "l": 34.0,
      "so": 0.0,
      "d": 164.0,
      "sac": 29.0,
      "sv": 49.0,
      "ip": 1045.3,
      "kB": 401.0
    },
    "AA": {
      "sb": 71.0,
      "hb": 29.0,
      "qs": 75.0,
      "r": 520.0,
      "kP": 1062.0,
      "rbi": 651.0,
      "gw": 55.0,
      "w": 73.0,
      "s": 569.0,
      "hr": 142.0,
      "hbp": 20.0,
      "er": 536.0,
      "cs": 62.0,
      "bs": 14.0,
      "hd": 70.0,
      "bbP": 387.0,
      "bbB": 199.0,
      "t": 48.0,
      "hP": 1120.0,
      "l": 55.0,
      "so": 0.0,
      "d": 181.0,
      "sac": 30.0,
      "sv": 35.0,
      "ip": 1153.3,
      "kB": 468.0
    },
    "JK": {
      "sb": 92.0,
      "hb": 16.0,
      "qs": 67.0,
      "r": 572.0,
      "kP": 1068.0,
      "rbi": 666.0,
      "gw": 32.0,
      "w": 72.0,
      "s": 576.0,
      "hr": 157.0,
      "hbp": 24.0,
      "er": 476.0,
      "cs": 65.0,
      "bs": 6.0,
      "hd": 61.0,
      "bbP": 387.0,
      "bbB": 203.0,
      "t": 37.0,
      "hP": 935.0,
      "l": 58.0,
      "so": 1.0,
      "d": 176.0,
      "sac": 30.0,
      "sv": 37.0,
      "ip": 1052.0,
      "kB": 455.0
    },
    "MN": {
      "sb": 122.0,
      "hb": 18.0,
      "qs": 75.0,
      "r": 552.0,
      "kP": 1087.0,
      "rbi": 709.0,
      "gw": 39.0,
      "w": 68.0,
      "s": 658.0,
      "hr": 170.0,
      "hbp": 28.0,
      "er": 538.0,
      "cs": 59.0,
      "bs": 12.0,
      "hd": 70.0,
      "bbP": 409.0,
      "bbB": 202.0,
      "t": 70.0,
      "hP": 1014.0,
      "l": 70.0,
      "so": 1.0,
      "d": 179.0,
      "sac": 38.0,
      "sv": 39.0,
      "ip": 1149.0,
      "kB": 510.0
    },
    "SK": {
      "sb": 73.0,
      "hb": 26.0,
      "qs": 66.0,
      "r": 524.0,
      "kP": 1164.0,
      "rbi": 704.0,
      "gw": 46.0,
      "w": 71.0,
      "s": 574.0,
      "hr": 139.0,
      "hbp": 12.0,
      "er": 535.0,
      "cs": 60.0,
      "bs": 11.0,
      "hd": 61.0,
      "bbP": 392.0,
      "bbB": 176.0,
      "t": 52.0,
      "hP": 1070.0,
      "l": 39.0,
      "so": 2.0,
      "d": 180.0,
      "sac": 25.0,
      "sv": 38.0,
      "ip": 1106.3,
      "kB": 424.0
    },
    "SP": {
      "sb": 109.0,
      "hb": 15.0,
      "qs": 80.0,
      "r": 536.0,
      "kP": 1141.0,
      "rbi": 661.0,
      "gw": 36.0,
      "w": 73.0,
      "s": 624.0,
      "hr": 166.0,
      "hbp": 18.0,
      "er": 528.0,
      "cs": 58.0,
      "bs": 13.0,
      "hd": 63.0,
      "bbP": 426.0,
      "bbB": 187.0,
      "t": 47.0,
      "hP": 1102.0,
      "l": 34.0,
      "so": 0.0,
      "d": 179.0,
      "sac": 32.0,
      "sv": 42.0,
      "ip": 1167.3,
      "kB": 472.0
    },
    "IR": {
      "sb": 116.0,
      "hb": 37.0,
      "qs": 68.0,
      "r": 625.0,
      "kP": 929.0,
      "rbi": 685.0,
      "gw": 40.0,
      "w": 63.0,
      "s": 659.0,
      "hr": 195.0,
      "hbp": 26.0,
      "er": 457.0,
      "cs": 69.0,
      "bs": 8.0,
      "hd": 74.0,
      "bbP": 351.0,
      "bbB": 224.0,
      "t": 73.0,
      "hP": 950.0,
      "l": 41.0,
      "so": 0.0,
      "d": 168.0,
      "sac": 28.0,
      "sv": 17.0,
      "ip": 1044.7,
      "kB": 538.0
    },
    "DH": {
      "sb": 77.0,
      "hb": 43.0,
      "qs": 70.0,
      "r": 497.0,
      "kP": 1005.0,
      "rbi": 670.0,
      "gw": 29.0,
      "w": 77.0,
      "s": 566.0,
      "hr": 137.0,
      "hbp": 15.0,
      "er": 521.0,
      "cs": 62.0,
      "bs": 9.0,
      "hd": 62.0,
      "bbP": 424.0,
      "bbB": 202.0,
      "t": 52.0,
      "hP": 1056.0,
      "l": 44.0,
      "so": 1.0,
      "d": 174.0,
      "sac": 14.0,
      "sv": 27.0,
      "ip": 1140.0,
      "kB": 414.0
    },
    "MM": {
      "sb": 99.0,
      "hb": 17.0,
      "qs": 68.0,
      "r": 564.0,
      "kP": 1210.0,
      "rbi": 605.0,
      "gw": 31.0,
      "w": 64.0,
      "s": 519.0,
      "hr": 152.0,
      "hbp": 13.0,
      "er": 436.0,
      "cs": 65.0,
      "bs": 8.0,
      "hd": 78.0,
      "bbP": 336.0,
      "bbB": 173.0,
      "t": 50.0,
      "hP": 929.0,
      "l": 53.0,
      "so": 0.0,
      "d": 171.0,
      "sac": 25.0,
      "sv": 41.0,
      "ip": 1131.3,
      "kB": 410.0
    }
  },
  "teams": {
    "WG": {
      "name": "WITTnessing Greatness",
      "color": "#2a9d8f",
      "wins": 8,
      "losses": 5,
      "apW": 90,
      "scores": [
        656.5,
        354.5,
        394.0,
        508.0,
        469.5,
        381.0,
        427.5,
        467.5,
        514.5,
        472.5,
        402.0,
        408.5,
        485.0
      ],
      "score": 165.5,
      "starts": 3
    },
    "BB": {
      "name": "Back 2 Back CY Young",
      "color": "#e9c46a",
      "wins": 8,
      "losses": 5,
      "apW": 83,
      "scores": [
        522.5,
        325.5,
        478.0,
        469.0,
        476.5,
        333.0,
        406.0,
        460.5,
        497.0,
        389.5,
        508.5,
        447.0,
        559.0
      ],
      "score": 92.5,
      "starts": 2
    },
    "RM": {
      "name": "Raleighing My Way",
      "color": "#52b788",
      "wins": 4,
      "losses": 9,
      "apW": 41,
      "scores": [
        505.0,
        484.0,
        321.5,
        429.5,
        407.0,
        352.0,
        416.0,
        373.5,
        278.0,
        348.5,
        406.5,
        387.0,
        483.0
      ],
      "score": 138.5,
      "starts": 2
    },
    "TB": {
      "name": "Thicc Bois",
      "color": "#f4a261",
      "wins": 5,
      "losses": 8,
      "apW": 46,
      "scores": [
        506.0,
        363.0,
        481.5,
        501.5,
        327.5,
        379.5,
        367.0,
        350.5,
        501.5,
        281.0,
        360.0,
        219.0,
        469.5
      ],
      "score": 119.5,
      "starts": 2
    },
    "AA": {
      "name": "All ARRAEZ for the JUDGE",
      "color": "#6a4c93",
      "wins": 8,
      "losses": 5,
      "apW": 69,
      "scores": [
        646.5,
        537.0,
        296.0,
        391.5,
        494.5,
        413.5,
        403.0,
        402.0,
        409.0,
        341.0,
        433.0,
        481.5,
        433.5
      ],
      "score": 105.5,
      "starts": 4
    },
    "JK": {
      "name": "Jung H King",
      "color": "#ff6b6b",
      "wins": 8,
      "losses": 5,
      "apW": 76,
      "scores": [
        812.5,
        334.0,
        475.5,
        392.0,
        276.5,
        458.5,
        488.0,
        361.5,
        468.0,
        386.5,
        468.5,
        399.0,
        538.0
      ],
      "score": 50.0,
      "starts": 2
    },
    "MN": {
      "name": "MANNY MEN",
      "color": "#f77f00",
      "wins": 4,
      "losses": 9,
      "apW": 87,
      "scores": [
        723.0,
        546.5,
        401.0,
        501.0,
        409.0,
        428.0,
        444.0,
        397.0,
        452.0,
        426.5,
        504.0,
        456.0,
        287.5
      ],
      "score": 187.0,
      "starts": 5
    },
    "SK": {
      "name": "Stop looking at me Kwan",
      "color": "#4cc9f0",
      "wins": 3,
      "losses": 10,
      "apW": 62,
      "scores": [
        643.0,
        390.0,
        377.5,
        369.0,
        414.5,
        468.5,
        433.5,
        446.5,
        458.5,
        394.5,
        397.5,
        378.5,
        373.5
      ],
      "score": 138.5,
      "starts": 7
    },
    "SP": {
      "name": "16 percent",
      "color": "#90be6d",
      "wins": 6,
      "losses": 7,
      "apW": 73,
      "scores": [
        595.5,
        484.5,
        468.0,
        458.0,
        434.0,
        392.0,
        539.0,
        284.0,
        534.5,
        455.0,
        331.0,
        433.0,
        400.5
      ],
      "score": 167.0,
      "starts": 6
    },
    "IR": {
      "name": "Ima Ride For My MF McGGonicle",
      "color": "#e63946",
      "wins": 8,
      "losses": 5,
      "apW": 87,
      "scores": [
        755.0,
        538.5,
        554.0,
        411.0,
        409.5,
        443.5,
        397.5,
        472.0,
        385.0,
        411.0,
        477.0,
        464.5,
        369.0
      ],
      "score": 128.0,
      "starts": 6
    },
    "DH": {
      "name": "Dom's House of Fun",
      "color": "#a8dadc",
      "wins": 7,
      "losses": 6,
      "apW": 65,
      "scores": [
        603.5,
        300.5,
        510.5,
        310.0,
        438.5,
        376.0,
        399.0,
        474.0,
        337.5,
        387.0,
        436.0,
        502.0,
        436.5
      ],
      "score": 122.5,
      "starts": 3
    },
    "MM": {
      "name": "Mike and Mike In The Mornin'",
      "color": "#457b9d",
      "wins": 9,
      "losses": 4,
      "apW": 79,
      "scores": [
        567.5,
        467.5,
        475.0,
        461.5,
        449.0,
        401.0,
        370.5,
        425.5,
        399.5,
        496.5,
        456.5,
        506.0,
        403.0
      ],
      "score": 177.0,
      "starts": 4
    }
  },
  "supabaseUrl": "https://akppyivrfgfcwskfazuf.supabase.co",
  "supabaseAnonKey": "eyJhbGciOiJIUzI1NiIsInR5cCI6IkpXVCJ9.eyJpc3MiOiJzdXBhYmFzZSIsInJlZiI6ImFrcHB5aXZyZmdmY3dza2ZhenVmIiwicm9sZSI6ImFub24iLCJpYXQiOjE3Nzg1OTEwMjMsImV4cCI6MjA5NDE2NzAyM30.E6M4RjVCp9hGdsgSSDrqk_9KFeFkz1epoJ-RU7ulzWI"
}